README.md
setup.cfg
setup.py
deepstreamio_client/__init__.py
deepstreamio_client/client.py
deepstreamio_client/exceptions.py
deepstreamio_client.egg-info/PKG-INFO
deepstreamio_client.egg-info/SOURCES.txt
deepstreamio_client.egg-info/dependency_links.txt
deepstreamio_client.egg-info/not-zip-safe
deepstreamio_client.egg-info/requires.txt
deepstreamio_client.egg-info/top_level.txt