Metadata-Version: 1.1
Name: deepstreamio-client
Version: 0.1.1
Summary: Python client using the dsh HTTP API
Home-page: https://github.com/VojtechBartos/deepstream.io-client-python
Author: Vojtech Bartos
Author-email: hi@vojtech.me
License: MIT
Keywords: deepstream
Platform: any
Classifier: Development Status :: 4 - Beta
Classifier: Intended Audience :: Developers
Classifier: License :: OSI Approved :: MIT License
Classifier: Natural Language :: English
Classifier: Programming Language :: Python :: 2
Classifier: Programming Language :: Python :: 2.7
Classifier: Programming Language :: Python :: 3
Classifier: Programming Language :: Python :: 3.3
Classifier: Programming Language :: Python :: 3.4
Classifier: Programming Language :: Python :: 3.5
Classifier: Programming Language :: Python :: 3.6
